stock_watch-0.1.dist-info/licenses/LICENSE
stock_watcher/__main__.py
stock_watch-0.1.dist-info/METADATA
stock_watch-0.1.dist-info/WHEEL
stock_watch-0.1.dist-info/entry_points.txt
stock_watch-0.1.dist-info/top_level.txt
stock_watch-0.1.dist-info/RECORD
