Metadata-Version: 2.4
Name: stock_watch
Version: 0.1
Summary: Deliver live data for your portfolio in your terminal
Author-email: Drake Wiggins <drakewiggins2@gmail.com>
License-Expression: MIT
Project-URL: Homepage, https://github.com/Drake14W/stock-watcher
Project-URL: Issues, https://github.com/Drake14W/stock-watcher/issues
Classifier: Programming Language :: Python :: 3
Classifier: Operating System :: OS Independent
Requires-Python: >=3.8
License-File: LICENSE
Requires-Dist: yfinance>=0.2.55
Dynamic: license-file
